uex_api_sdk-1.0.1.dist-info/licenses/LICENSE
uexcorpapi/__init__.py
uexcorpapi/api_helper.py
uexcorpapi/configuration.py
uexcorpapi/uexcorpapi_client.py
uexcorpapi/controllers/__init__.py
uexcorpapi/controllers/base_controller.py
uexcorpapi/controllers/categories_attributes_controller.py
uexcorpapi/controllers/categories_controller.py
uexcorpapi/controllers/cities_controller.py
uexcorpapi/controllers/commodities_alerts_controller.py
uexcorpapi/controllers/commodities_controller.py
uexcorpapi/controllers/commodities_prices_all_controller.py
uexcorpapi/controllers/commodities_ranking_controller.py
uexcorpapi/controllers/commodities_raw_prices_all_controller.py
uexcorpapi/controllers/commodities_status_controller.py
uexcorpapi/controllers/companies_controller.py
uexcorpapi/controllers/contacts_controller.py
uexcorpapi/controllers/contracts_controller.py
uexcorpapi/controllers/data_extract_controller.py
uexcorpapi/controllers/data_parameters_controller.py
uexcorpapi/controllers/factions_controller.py
uexcorpapi/controllers/fleet_controller.py
uexcorpapi/controllers/fuel_prices_all_controller.py
uexcorpapi/controllers/game_versions_controller.py
uexcorpapi/controllers/items_prices_all_controller.py
uexcorpapi/controllers/jump_points_controller.py
uexcorpapi/controllers/jurisdictions_controller.py
uexcorpapi/controllers/m_commodity_code_controller.py
uexcorpapi/controllers/m_commodity_name_controller.py
uexcorpapi/controllers/m_commodity_slug_controller.py
uexcorpapi/controllers/m_id_category_controller.py
uexcorpapi/controllers/m_id_commodity_controller.py
uexcorpapi/controllers/m_id_company_controller.py
uexcorpapi/controllers/m_id_item_controller.py
uexcorpapi/controllers/m_id_orbit_origin_controller.py
uexcorpapi/controllers/m_id_organization_controller.py
uexcorpapi/controllers/m_id_planet_origin_controller.py
uexcorpapi/controllers/m_id_terminal_controller.py
uexcorpapi/controllers/m_id_terminal_origin_controller.py
uexcorpapi/controllers/m_size_controller.py
uexcorpapi/controllers/m_slug_controller.py
uex_api_sdk-1.0.1.dist-info/METADATA
uex_api_sdk-1.0.1.dist-info/WHEEL
uex_api_sdk-1.0.1.dist-info/top_level.txt
uex_api_sdk-1.0.1.dist-info/RECORD
