Metadata-Version: 2.4
Name: uex-api-sdk
Version: 1.0.1
Summary: UEX API
Author-email: KC85 <ghhqhg1cv@mozmail.com>
Project-URL: Documentation, https://uex.com
Requires-Python: >=3.7
License-File: LICENSE
Requires-Dist: apimatic-core>=0.2.20,~=0.2.0
Requires-Dist: apimatic-core-interfaces>=0.1.5,~=0.1.0
Requires-Dist: apimatic-requests-client-adapter>=0.1.6,~=0.1.0
Provides-Extra: testutils
Requires-Dist: pytest>=7.2.2; extra == "testutils"
Dynamic: license-file
